pyrigee/__init__.py
pyrigee/body.py
pyrigee/craft.py
pyrigee/maneuver.py
pyrigee/orbit.py
pyrigee/orbit_plotter.py
pyrigee/plotting_calculator.py
pyrigee-1.0.4.dist-info/LICENSE
pyrigee-1.0.4.dist-info/METADATA
pyrigee-1.0.4.dist-info/WHEEL
pyrigee-1.0.4.dist-info/top_level.txt
pyrigee-1.0.4.dist-info/RECORD
