Metadata-Version: 2.1
Name: pyrigee
Version: 1.0.4
Summary: A python package for visualizing spacecraft orbits and orbital maneuvers.
Home-page: https://github.com/JackCSheehan/pyrigee
Author: Jack Sheehan
License: UNKNOWN
Platform: UNKNOWN
Classifier: Programming Language :: Python :: 3
Classifier: License :: OSI Approved :: MIT License
Classifier: Topic :: Scientific/Engineering :: Astronomy
Classifier: Topic :: Scientific/Engineering :: Visualization
Requires-Python: >=3.6
